git_pp/__init__.py
git_pp/__main__.py
git_pp/git_pp.py
git_pp/git_pre_pull.py
git_pp/git_push_to_all_remotes.py
git_pp-2.0.0.dist-info/LICENSE
git_pp-2.0.0.dist-info/METADATA
git_pp-2.0.0.dist-info/WHEEL
git_pp-2.0.0.dist-info/entry_points.txt
git_pp-2.0.0.dist-info/RECORD
