Metadata-Version: 2.1
Name: git-pp
Version: 2.0.0
Summary: A (tiny) Git utility for auto-committing and concurrent pushing
Home-page: https://github.com/tddschn/git-pp
License: MIT
Keywords: git,asyncio
Author: Xinyuan Chen
Author-email: 45612704+tddschn@users.noreply.github.com
Requires-Python: >=3.10,<4.0
Classifier: Environment :: Console
Classifier: Framework :: AsyncIO
Classifier: License :: OSI Approved :: MIT License
Classifier: Operating System :: Unix
Classifier: Programming Language :: Python :: 3
Classifier: Programming Language :: Python :: 3.10
Classifier: Programming Language :: Python :: 3.11
Classifier: Programming Language :: Python :: 3.12
Classifier: Programming Language :: Python :: 3.13
Classifier: Topic :: Software Development :: Version Control :: Git
Classifier: Typing :: Typed
Provides-Extra: uvloop
Requires-Dist: utils-tddschn (>=1.0.4,<2.0.0)
Requires-Dist: uvloop (>=0.16.0,<0.17.0) ; extra == "uvloop"
Project-URL: Bug Tracker, https://github.com/tddschn/git-pp/issues
Project-URL: Repository, https://github.com/tddschn/git-pp
